ZhonggouGaishanJiyouDaimaDeSheji2ndFix1/README.md
ZhonggouGaishanJiyouDaimaDeSheji2ndFix1/__init__.py
ZhonggouGaishanJiyouDaimaDeSheji2ndFix1/__main__.py
ZhonggouGaishanJiyouDaimaDeSheji2ndFix1/file.epub
ZhonggouGaishanJiyouDaimaDeSheji2ndFix1/index.html
ZhonggouGaishanJiyouDaimaDeSheji2ndFix1/css/__init__.py
ZhonggouGaishanJiyouDaimaDeSheji2ndFix1/css/annotations.css
ZhonggouGaishanJiyouDaimaDeSheji2ndFix1/css/main.css
ZhonggouGaishanJiyouDaimaDeSheji2ndFix1/css/normalize.css
ZhonggouGaishanJiyouDaimaDeSheji2ndFix1/css/popup.css
ZhonggouGaishanJiyouDaimaDeSheji2ndFix1/font/__init__.py
ZhonggouGaishanJiyouDaimaDeSheji2ndFix1/font/fontello.eot
ZhonggouGaishanJiyouDaimaDeSheji2ndFix1/font/fontello.svg
ZhonggouGaishanJiyouDaimaDeSheji2ndFix1/font/fontello.ttf
ZhonggouGaishanJiyouDaimaDeSheji2ndFix1/font/fontello.woff
ZhonggouGaishanJiyouDaimaDeSheji2ndFix1/img/__init__.py
ZhonggouGaishanJiyouDaimaDeSheji2ndFix1/img/annotator-glyph-sprite.png
ZhonggouGaishanJiyouDaimaDeSheji2ndFix1/img/annotator-icon-sprite.png
ZhonggouGaishanJiyouDaimaDeSheji2ndFix1/img/apple-touch-icon.png
ZhonggouGaishanJiyouDaimaDeSheji2ndFix1/img/cancelfullscreen.png
ZhonggouGaishanJiyouDaimaDeSheji2ndFix1/img/close.png
ZhonggouGaishanJiyouDaimaDeSheji2ndFix1/img/fullscreen.png
ZhonggouGaishanJiyouDaimaDeSheji2ndFix1/img/loader.gif
ZhonggouGaishanJiyouDaimaDeSheji2ndFix1/img/menu-icon.png
ZhonggouGaishanJiyouDaimaDeSheji2ndFix1/img/save.png
ZhonggouGaishanJiyouDaimaDeSheji2ndFix1/img/saved.png
ZhonggouGaishanJiyouDaimaDeSheji2ndFix1/img/settings-s.png
ZhonggouGaishanJiyouDaimaDeSheji2ndFix1/img/settings.png
ZhonggouGaishanJiyouDaimaDeSheji2ndFix1/img/star.png
ZhonggouGaishanJiyouDaimaDeSheji2ndFix1/js/__init__.py
ZhonggouGaishanJiyouDaimaDeSheji2ndFix1/js/epub.js
ZhonggouGaishanJiyouDaimaDeSheji2ndFix1/js/epub.min.js
ZhonggouGaishanJiyouDaimaDeSheji2ndFix1/js/epub.min.map
ZhonggouGaishanJiyouDaimaDeSheji2ndFix1/js/hooks.min.js
ZhonggouGaishanJiyouDaimaDeSheji2ndFix1/js/hooks.min.map
zhonggou_gaishan_jiyou_daima_de_sheji_2nd_fix1-2025.3.24.1.dist-info/METADATA
zhonggou_gaishan_jiyou_daima_de_sheji_2nd_fix1-2025.3.24.1.dist-info/WHEEL
zhonggou_gaishan_jiyou_daima_de_sheji_2nd_fix1-2025.3.24.1.dist-info/entry_points.txt
zhonggou_gaishan_jiyou_daima_de_sheji_2nd_fix1-2025.3.24.1.dist-info/top_level.txt
zhonggou_gaishan_jiyou_daima_de_sheji_2nd_fix1-2025.3.24.1.dist-info/RECORD
